agl_anonymizer_pipeline/.DS_Store
agl_anonymizer_pipeline/.gitignore
agl_anonymizer_pipeline/README.md
agl_anonymizer_pipeline/__init__.py
agl_anonymizer_pipeline/blur.py
agl_anonymizer_pipeline/box_operations.py
agl_anonymizer_pipeline/citations.bib
agl_anonymizer_pipeline/custom_logger.py
agl_anonymizer_pipeline/device_reader.py
agl_anonymizer_pipeline/devices/default.json
agl_anonymizer_pipeline/devices/olympus_cv_1500.json
agl_anonymizer_pipeline/directory_setup.py
agl_anonymizer_pipeline/east_text_detection.py
agl_anonymizer_pipeline/flair_NER.py
agl_anonymizer_pipeline/image_reassembly.py
agl_anonymizer_pipeline/main.py
agl_anonymizer_pipeline/names_adder.py
agl_anonymizer_pipeline/names_dict/ascii.py
agl_anonymizer_pipeline/names_dict/first_and_last_names_female.txt
agl_anonymizer_pipeline/names_dict/first_and_last_names_female_ascii.txt
agl_anonymizer_pipeline/names_dict/first_and_last_names_male.txt
agl_anonymizer_pipeline/names_dict/first_and_last_names_male_ascii.txt
agl_anonymizer_pipeline/names_dict/first_and_last_names_neutral_ascii.txt
agl_anonymizer_pipeline/names_dict/first_names_female.txt
agl_anonymizer_pipeline/names_dict/first_names_female_ascii.txt
agl_anonymizer_pipeline/names_dict/first_names_male.txt
agl_anonymizer_pipeline/names_dict/first_names_male_ascii.txt
agl_anonymizer_pipeline/names_dict/first_names_neutral.txt
agl_anonymizer_pipeline/names_dict/first_names_neutral_ascii.txt
agl_anonymizer_pipeline/names_dict/firstandlastword/fn.py
agl_anonymizer_pipeline/names_dict/firstandlastword/ln.py
agl_anonymizer_pipeline/names_dict/last_names_female.txt
agl_anonymizer_pipeline/names_dict/last_names_female_ascii.txt
agl_anonymizer_pipeline/names_dict/last_names_male.txt
agl_anonymizer_pipeline/names_dict/last_names_male_ascii.txt
agl_anonymizer_pipeline/names_dict/last_names_neutral.txt
agl_anonymizer_pipeline/names_dict/last_names_neutral_ascii.txt
agl_anonymizer_pipeline/names_generator.py
agl_anonymizer_pipeline/ocr.py
agl_anonymizer_pipeline-0.1.11.dist-info/METADATA
agl_anonymizer_pipeline-0.1.11.dist-info/WHEEL
agl_anonymizer_pipeline-0.1.11.dist-info/RECORD
