Metadata-Version: 2.1
Name: agl_anonymizer_pipeline
Version: 0.1.11
Summary: This package is made to censor sensitive data in images and extract the contents. NER is planned for the future.
License: MIT
Author: maxhild
Author-email: 58726316+maxhild@users.noreply.github.com
Requires-Python: >=3.11,<4.0
Classifier: License :: OSI Approved :: MIT License
Classifier: Programming Language :: Python :: 3
Classifier: Programming Language :: Python :: 3.11
Classifier: Programming Language :: Python :: 3.12
Requires-Dist: flair (>=0.14.0,<0.15.0)
Requires-Dist: gender-guesser (>=0.4.0,<0.5.0)
Requires-Dist: gensim (>=4.3.3,<5.0.0)
Requires-Dist: imutils (>=0.5.4,<0.6.0)
Requires-Dist: numpy (==1.26.4)
Requires-Dist: opencv-python (>=4.9.0.80,<5.0.0.0)
Requires-Dist: pytesseract (>=0.3.13,<0.4.0)
Requires-Dist: spacy (==3.7.5)
Requires-Dist: spacy-lookups-data (>=1.0.5,<2.0.0)
Requires-Dist: transformers (>=4.45.0,<5.0.0)
